django_scrumboard/__init__.py
django_scrumboard/forms.py
django_scrumboard/models.py
django_scrumboard/urls.py
django_scrumboard/views.py
django_scrumboard/migrations/0001_initial.py
django_scrumboard/migrations/0002_task_status.py
django_scrumboard/migrations/__init__.py
django_scrumboard/static/css/django_scrumboard.css
django_scrumboard/static/css/django_scrumboard.scss
django_scrumboard/static/img/bin.svg
django_scrumboard/static/img/development-expand.svg
django_scrumboard/static/img/github.svg
django_scrumboard/static/img/info.svg
django_scrumboard/static/img/pending-expand.svg
django_scrumboard/static/img/plus.svg
django_scrumboard/static/img/production-expand.svg
django_scrumboard/static/img/rejected-expand.svg
django_scrumboard/static/img/testing-expand.svg
django_scrumboard/static/js/django_scrumboard.js
django_scrumboard/static/js/helper.js
django_scrumboard/static/js/localstorage.js
django_scrumboard/static/js/remotestorage.js
django_scrumboard/static/js/lib/handlebars-v4.0.5.js
django_scrumboard/templates/django_scrumboard/base.html
django_scrumboard/templates/django_scrumboard/index.html
django_scrumboard-0.1.1.dist-info/DESCRIPTION.rst
django_scrumboard-0.1.1.dist-info/METADATA
django_scrumboard-0.1.1.dist-info/RECORD
django_scrumboard-0.1.1.dist-info/WHEEL
django_scrumboard-0.1.1.dist-info/metadata.json
django_scrumboard-0.1.1.dist-info/top_level.txt
